{
  "summary": {
    "totalCompanies": 74,
    "totalSnapshots": 259,
    "avgLinesOfCode": 140799.57915057914,
    "avgComplexity": 29948.837837837837,
    "seriesBSuccessRate": 71.62162162162163,
    "avgCodebaseAge": 1500.868725868726,
    "topLanguages": [
      {
        "language": "LANGUAGE_GO",
        "usage": 101881
      },
      {
        "language": "LANGUAGE_JAVASCRIPT",
        "usage": 38345
      },
      {
        "language": "LANGUAGE_JAVA",
        "usage": 31202
      },
      {
        "language": "LANGUAGE_PYTHON",
        "usage": 13316
      },
      {
        "language": "LANGUAGE_TYPESCRIPT",
        "usage": 12614
      }
    ]
  },
  "keyInsights": [
    "Analyzed 74 companies with 259 code snapshots",
    "Average codebase size: 140.8K lines of code",
    "Average codebase age: 1501 days",
    "Top programming language: LANGUAGE_GO",
    "Strongest correlation: Positive very strong correlation between Lines of Code and Complexity (r=0.821)"
  ],
  "strongestCorrelations": [
    {
      "metric1": "Lines of Code",
      "metric2": "Complexity",
      "correlation": 0.8206871125152173,
      "strength": "Very Strong",
      "insight": "Positive very strong correlation between Lines of Code and Complexity"
    },
    {
      "metric1": "Lines of Code",
      "metric2": "Total Functions",
      "correlation": 0.7889069092679888,
      "strength": "Very Strong",
      "insight": "Positive very strong correlation between Lines of Code and Total Functions"
    },
    {
      "metric1": "Complexity",
      "metric2": "Total Functions",
      "correlation": 0.7315361319884488,
      "strength": "Very Strong",
      "insight": "Positive very strong correlation between Complexity and Total Functions"
    },
    {
      "metric1": "Codebase Age",
      "metric2": "Total Functions",
      "correlation": 0.5619237956124153,
      "strength": "Strong",
      "insight": "Positive strong correlation between Codebase Age and Total Functions"
    },
    {
      "metric1": "Lines of Code",
      "metric2": "Codebase Age",
      "correlation": 0.4947923621327276,
      "strength": "Moderate",
      "insight": "Positive moderate correlation between Lines of Code and Codebase Age"
    }
  ],
  "exportDate": "2025-09-08T13:25:31.896Z"
}